MuonDataLib/__init__.py
MuonDataLib/GUI/help.py
MuonDataLib/GUI/launch.py
MuonDataLib/GUI/main_GUI.py
MuonDataLib/GUI/presenter_template.py
MuonDataLib/GUI/view_template.py
MuonDataLib/GUI/filters/presenter.py
MuonDataLib/GUI/filters/view.py
MuonDataLib/GUI/load_bar/presenter.py
MuonDataLib/GUI/load_bar/view.py
MuonDataLib/GUI/main_app/presenter.py
MuonDataLib/GUI/main_app/view.py
MuonDataLib/GUI/plot_area/presenter.py
MuonDataLib/GUI/plot_area/view.py
MuonDataLib/GUI/save_bar/presenter.py
MuonDataLib/GUI/save_bar/view.py
MuonDataLib/GUI/utils/main_window.py
MuonDataLib/GUI/utils/worker.py
MuonDataLib/cython_ext/__init__.py
MuonDataLib/cython_ext/base_sample_logs.cp311-win_amd64.pyd
MuonDataLib/cython_ext/base_sample_logs.pyx
MuonDataLib/cython_ext/event_data.cp311-win_amd64.pyd
MuonDataLib/cython_ext/event_data.pyx
MuonDataLib/cython_ext/events_cache.cp311-win_amd64.pyd
MuonDataLib/cython_ext/events_cache.pyx
MuonDataLib/cython_ext/filter.cp311-win_amd64.pyd
MuonDataLib/cython_ext/filter.pyx
MuonDataLib/cython_ext/load_events.cp311-win_amd64.pyd
MuonDataLib/cython_ext/load_events.pyx
MuonDataLib/cython_ext/stats.cp311-win_amd64.pyd
MuonDataLib/cython_ext/stats.pyx
MuonDataLib/cython_ext/utils.cp311-win_amd64.pyd
MuonDataLib/cython_ext/utils.pyx
MuonDataLib/data/__init__.py
MuonDataLib/data/detector1.py
MuonDataLib/data/hdf5.py
MuonDataLib/data/muon_data.py
MuonDataLib/data/periods.py
MuonDataLib/data/raw_data.py
MuonDataLib/data/sample.py
MuonDataLib/data/sample_logs.py
MuonDataLib/data/source.py
MuonDataLib/data/user.py
MuonDataLib/data/utils.py
MuonDataLib/data/loader/__init__.py
MuonDataLib/data/loader/load_events.py
MuonDataLib/data/loader/load_nxs2.py
MuonDataLib/help/__init__.py
MuonDataLib/help/figure.py
MuonDataLib/help/help.py
MuonDataLib/help/help_docs.py
MuonDataLib/help/load_events.py
MuonDataLib/help/muon_data.py
MuonDataLib/help/utils.py
MuonDataLib/plot/__init__.py
MuonDataLib/plot/basic.py
MuonDataLib/test_helpers/GUI.py
muondatalib-0.9.2b11.dist-info/METADATA
muondatalib-0.9.2b11.dist-info/WHEEL
muondatalib-0.9.2b11.dist-info/top_level.txt
muondatalib-0.9.2b11.dist-info/RECORD
