Metadata-Version: 2.1
Name: muondatalib
Version: 0.9.2b11
Summary: Reading and writing for ISIS muon experiments.
Author-email: Anthony Lim <anthony.lim@stfc.ac.uk>
License: BSD
Requires: numpy
Requires: cython
Requires: plotly
Requires-Python: >=3.8
Requires-Dist: numpy
Requires-Dist: h5py
Requires-Dist: plotly
Requires-Dist: cython
Requires-Dist: pyqt5
Requires-Dist: dash[testing]
Requires-Dist: dash_bootstrap_components
Requires-Dist: pyqtwebengine
Requires-Dist: dash_daq
